[
    {
        "soal": "Selain mobil, bus, pesawat, orang pergi dari Jakarta ke Surabaya biasanya menggunakan?",
        "jawaban": "Celana"
    },
    {
        "soal": "Di rumah makan padang, selain pakai sendok kita makan pakai?",
        "jawaban": "Tenaga"
    },
    {
        "soal": "Biasa digunakan untuk menyalakan atau mematikan TV dan AC?",
        "jawaban": "Tolong"
    },
    {
        "soal": "Seseorang yang memimpin sebuah desa, biasanya dipanggil pak?",
        "jawaban": "Noleh"
    },
    {
        "soal": "Senikmat-nikmatnya makan diluar lebih nikmat makan di?",
        "jawaban": "Telan"
    },
    {
        "soal": "Makan duit rakyat disebut?",
        "jawaban": "Debus"
    },
    {
        "soal": "Ikan bernafas di air dengan?",
        "jawaban": "Tenang"
    },
    {
        "soal": "Binatang yang hinggap di makanan?",
        "jawaban": "Lapar"
    },
    {
        "soal": "Di dalam perpustakaan tidak boleh?",
        "jawaban": "Keramas"
    },
    {
        "soal": "Saat sukuran biasanya kita menyediakan?",
        "jawaban": "Ruangan"
    },
    {
        "soal": "Hewan laut yang jalannya miring dan bersembunyi di batu atau pasir biasanya?",
        "jawaban": "Lagi malu"
    },
    {
        "soal": "Kerbau adalah binatang yang memiliki?",
        "jawaban": "Huruf k"
    },
    {
        "soal": "Saat naik pesawat kita dilarang membawa..?",
        "jawaban": "Sendiri"
    },
    {
        "soal": "Seorang istri akan merasa terkejut bila di hari ulang tahun dibelikan?",
        "jawaban": "Beruang"
    },
    {
        "soal": "Seorang barber mencukur rambut pelanggan dengan?",
        "jawaban": "Gantian"
    },
    {
        "soal": "Buah yang dipotong-potong, diuleg campur gula jawa dan cabai, jadinya?",
        "jawaban": "Rusak"
    },
    {
        "soal": "Lorenzo, Marquez, rossi kejar-kejaran, salip menyalip di?",
        "jawaban": "Biarkan"
    },
    {
        "soal": "Mie ramen adalah makanan khas yang berasal dari?",
        "jawaban": "Mentah"
    },
    {
        "soal": "Hewan yang sehari-harinya memakan daging, dan hidup di rawa-rawa, namanya?",
        "jawaban": "Butuh"
    },
    {
        "soal": "Nasi yang enak buat sarapan, biasanya nasi?",
        "jawaban": "Matang"
    },
    {
        "soal": "Permen apa yang bagian gulanya ada di luar, tapi bungkusnya justru di dalam?",
        "jawaban": "Permen salah bikin"
    },
    {
        "soal": "Apa yang bulat, kecil, kadang hitam, kadang putih, terus kalau dipencet bisa keluar orangnya?",
        "jawaban": "Bel rumah"
    },
    {
        "soal": "Pintu apa yang didorong lima orang tetap tidak mau terbuka?",
        "jawaban": "Pintu yang tulisannya TARIK"
    },
    {
        "soal": "Jauh di mata, tapi dekat di hati, apakah itu?",
        "jawaban": "Usus"
    },
    {
        "soal": "Gajah naik motor keliatan apanya?",
        "jawaban": "Bohongnya"
    },
    {
        "soal": "Cermin jika di lap jadi…?",
        "jawaban": "Cermin"
    },
    {
        "soal": "Pedagang kaki lima bubar karena ada…?",
        "jawaban": "Macan"
    },
    {
        "soal": "Buah buah apa yang tua?",
        "jawaban": "Singkong"
    },
    {
        "soal": "Salah satu contoh hewan yang jalannya lambat?",
        "jawaban": "Serigala",
        "deskripsi": "Serigala kalau lagi jalan ya pelan-pelan, kalau lari baru cepet"
    },
    {
        "soal": "Lawannya gemuk?",
        "jawaban": "Takut",
        "deskripsi": "lah, takut kalau lawannya gemuk"
    },
    {
        "soal": "Koran disebut surat ?",
        "jawaban": "Salah",
        "deskripsi": "Masa koran disebut surat, salah dong"
    },
    {
        "soal": "Sebelum jadi katak, anak katak disebut ?",
        "jawaban": "Remaja",
        "deskripsi": "Nah proses sebelum menjadi katak dewasa, anak katak harus melalui masa-masa remaja dulu kan..."
    },
    {
        "soal": "Hewan berkaki delapan, yang bergelantungan ke sana kemari dengan jaring, namanya?",
        "jawaban": "Olahraga"
    },
    {
        "soal": "Burung bisa terbang karena memiliki?",
        "jawaban": "Bakat"
    },
    {
        "soal": "Kita tidak bisa menelepon, kalau handphonenya ngga ada?",
        "jawaban": "Angka"
    },
    {
        "soal": "Yang dibeli seorang cowok untuk pasangannya di saat Valentine biasanya?",
        "jawaban": "Bayar"
    },
    {
        "soal": "Saat ke Jakarta naik kereta, selain Stasiun Jatinegara, Stasiun Juanda, dan Pasar Senen, kita bisa turun di?",
        "jawaban": "Lantai"
    },
    {
        "soal": "Seorang pejabat akan terkena masalah kalau tersangkut?",
        "jawaban": "Jemuran"
    },
    {
        "soal": "Hewan yang sering digunakan petani untuk membajak sawah?",
        "jawaban": "Pasrah"
    },
    {
        "soal": "Neil Amstrong adalah astronot yang pernah menginjakkan kakinya di?",
        "jawaban": "Rumah"
    },
    {
        "soal": "Cuci piring harus?",
        "jawaban": "Sadar"
    },
    {
        "soal": "Setelah lulus SMA biasanya lanjut?",
        "jawaban": "Pulang"
    },
    {
        "soal": "Kalau semut kecil, gajah...?",
        "jawaban": "hewan"
    },
    {
        "soal": "Bertamu lebih dari 2x24 jam harus?",
        "jawaban": "Makan"
    },
    {
        "soal": "Yang dilakukan atlet sebelum bertanding?",
        "jawaban": "Pamitan"
    },
    {
        "soal": "Mulutmu ………..",
        "jawaban": "Hanyasatu",
        "deskripsi": "Mulut kan emang cuma satu"
    },
    {
        "soal": "Ada udang di balik…",
        "jawaban": "Gnadu",
        "deskripsi": "Itu fakta"
    },
    {
        "soal": "Es es apa yang bisa jalan?",
        "jawaban": "Eskalator",
        "deskripsi": "Kalau ga jalan bukan es kalator tapi tangga kalator"
    },
    {
        "soal": "Hati senang walaupun tak punya...",
        "jawaban": "Kaca",
        "deskripsi": "Kaca juga gak penting penting amat"
    },
    {
        "soal": "Suami bu camat?",
        "jawaban": "Laki",
        "deskripsi": "Karena kalo gak laki lesbi, dosa…"
    },
    {
        "soal": "Yang menyebabkan haus saat romadhon?",
        "jawaban": "Cuaca",
        "deskripsi": "Kalo panas pasti bikin haus, kalau puasa laper juga yah…"
    },
    {
        "soal": "Kirimin uang lewat atm?",
        "jawaban": "Thanksya",
        "deskripsi": "Thanks ya sudah diterima"
    },
    {
        "soal": "Rizky febian lahir di...",
        "jawaban": "Gendong",
        "deskripsi": "Ya di gendong dulu lah masa langsung di mandiin"
    },
    {
        "soal": "Para pejuang melawan penjajah dengan senjata?",
        "jawaban": "Bikin sendiri",
        "deskripsi": "Klo gak bikin sendiri lah trus dibikinin siapa?"
    },
    {
        "soal": "Apa yang tidak boleh di bawa ke pesawat?",
        "jawaban": "Sendiri",
        "deskripsi": "Karena kalo kita bawa sendiri nanti jatuh"
    },
    {
        "soal": "Tak kenal maka tak...",
        "jawaban": "Undang",
        "deskripsi": "Orang tidak kenal masak di undang"
    },
    {
        "soal": "Hewan yang melolong dimalam hari…",
        "jawaban": "Terinjak",
        "deskripsi": "Kasian kaki nya keinjak"
    },
    {
        "soal": "Api dipegang terasa?",
        "jawaban": "Susah",
        "deskripsi": "Api dipegang susah lah panas lagi"
    },
    {
        "soal": "Di akuarium ada ikan 10 mati 2 tinggal",
        "jawaban": "Dibuang",
        "deskripsi": "Kalo tidak dibuang, ikan yang laen jadi ikutan mati"
    },
    {
        "soal": "Tidak masuk kerja karena hari...",
        "jawaban": "DiPHK",
        "deskripsi": "Ya kan si hari kalo di phk ga usah masuk kerja lagi..."
    },
    {
        "soal": "Tinky winky...",
        "jawaban": "Tenar sekali",
        "deskripsi": "Nama nama tersebut sudah terkenal di semua kalangan"
    },
    {
        "soal": "Cicak jatuh ke…",
        "jawaban": "Bacok",
        "deskripsi": "Di bacok mah jatuh"
    },
    {
        "soal": "Dalam permainan bulutangkis",
        "jawaban": "Iya",
        "deskripsi": "Coba nonton bulutangkis pasti nama indonesia disingkat"
    },
    {
        "soal": "Ada guling ada…",
        "jawaban": "Benang",
        "deskripsi": "Kalo ga ada benang jahitnya pake apa?"
    },
    {
        "soal": "Andi basah kuyup karena?",
        "jawaban": "Husen",
        "deskripsi": "Karena diceburin si husen ke kolam, nakal banget yah…"
    },
    {
        "soal": "Matahari terbenam hari mulai",
        "jawaban": "Pulang",
        "deskripsi": "Udah malam kalo gak pulang, hari dicariin ibunya"
    },
    {
        "soal": "Hewan pemakan segala?",
        "jawaban": "Rakus",
        "deskripsi": "Semuanya dimakan"
    },
    {
        "soal": "Burung terbang menggunakan..",
        "jawaban": "Semangat",
        "deskripsi": "Kalau tidak semangat pasti lemes tuh.."
    },
    {
        "soal": "Beli lampu biasanya di...",
        "jawaban": "Coba",
        "deskripsi": "Anda kalau beli lampu pasti dicoba dulu"
    },
    {
        "soal": "Jangan berteman dengan orang...",
        "jawaban": "Hilang",
        "deskripsi": "Gimana caranya?"
    },
    {
        "soal": "Alpukat",
        "jawaban": "Bisa",
        "deskripsi": "Memang bisa disebut"
    },
    {
        "soal": "Bekas pacar disebut...",
        "jawaban": "Jangan",
        "deskripsi": "Nanti pacar yang sekarang marah"
    },
    {
        "soal": "Orang sakit minum?",
        "jawaban": "Oiya",
        "deskripsi": "Sakit minum yang banyak yah, biar cepet sembuh"
    },
    {
        "soal": "Pelat nomer kendaraan A berasal dari?",
        "jawaban": "Samsat",
        "deskripsi": "Karena samsat merupakan institusi yg berhak mengeluarkan plat kendaraan bermotor"
    },
    {
        "soal": "Hujan deres bikin …",
        "jawaban": "Basah",
        "deskripsi": "Kalau panas pasti kering"
    },
    {
        "soal": "Makan dianjurkan pakai tangan…",
        "jawaban": "Benar",
        "deskripsi": "Kanan atau kiri boleh kok, kanan lebih bagus sih katanya"
    },
    {
        "soal": "Pesawat mendarat di…",
        "jawaban": "Bantuin",
        "deskripsi": "Pilot, co-pilot, operator bandara, dan lain-lain.."
    },
    {
        "soal": "Di rumah ada adik",
        "jawaban": "Masak",
        "deskripsi": "Hmm kira kira lagi masak apa yah…"
    },
    {
        "soal": "Kakak mengantar adik sekolah sampai",
        "jawaban": "Capek",
        "deskripsi": "Nganter nya di gendong"
    },
    {
        "soal": "Galang menyimpan buku di…",
        "jawaban": "Mas",
        "deskripsi": "Bukunya dimas dipinjam galang kemarin sore"
    },
    {
        "soal": "Matahari tenggelam di sebelah…",
        "jawaban": "Gawat",
        "deskripsi": "Gawat kalau matahari tenggelam di sebelah kita"
    },
    {
        "soal": "Apabila mengendarai mobil wajib bawa",
        "jawaban": "Satu",
        "deskripsi": "Kalo bawa 2 gimana mengendarainya"
    },
    {
        "soal": "Mawar melati semuanya…",
        "jawaban": "Bunga",
        "deskripsi": "Kalo bukan bunga apa coba, hewan?"
    },
    {
        "soal": "Jangan membuang tisu di…",
        "jawaban": "Tempatnya",
        "deskripsi": "Masih di tempatnya kok di buang"
    },
    {
        "soal": "Ketika _____ orang biasanya makan",
        "jawaban": "Marah",
        "deskripsi": "Orang marah apa enggak ya pasti makan"
    },
    {
        "soal": "Burung adalah hewan yang bisa..",
        "jawaban": "Temenan",
        "deskripsi": "Kan kalo terbang rame-rame kan sama temennya.."
    },
    {
        "soal": "Hewan yang suka buka mulut lebar",
        "jawaban": "Kenaflu",
        "deskripsi": "Itu karena ga bisa napas idungnya mampet.."
    },
    {
        "soal": "Hewan yang berubah warna kalau ada musuhnya?",
        "jawaban": "Bengong",
        "deskripsi": "Karena, musuhnya bengong lihat hewan berubah warna"
    },
    {
        "soal": "Artis wanita yang punya kumis tipis",
        "jawaban": "Ihkumisan",
        "deskripsi": "Ih kok kumisan sih.."
    },
    {
        "soal": "Pintu biasa di….",
        "jawaban": "Tekan",
        "deskripsi": "Kalau anda biasa ke atm kan pin ditekan"
    },
    {
        "soal": "Lebak bulus",
        "jawaban": "Terkenal",
        "deskripsi": " Karena lebak bulus,cililitan semua orang tau maka nya terkenal"
    },
    {
        "soal": "Seorang matador bisa terluka karena diseruduk..",
        "jawaban": "Biskota",
        "deskripsi": "Mau banteng, mau bis kota, tetep aja bisa terluka.."
    },
    {
        "soal": "Cermin jika di lap jadi…",
        "jawaban": "Cermin",
        "deskripsi": "Ya masa berubah, yaal tetap cermin"
    },
    {
        "soal": "Batik merupakan produk asli dari…",
        "jawaban": "Manusia",
        "deskripsi": "Sejauh ini belum ada mahluk lain yang bisa"
    },
    {
        "soal": "Kendaraan yang suka dipake tukang ojek?",
        "jawaban": "Mogok",
        "deskripsi": "Motor emang suka mogok"
    },
    {
        "soal": "Binatang apa yang ga bisa bergerak?",
        "jawaban": "Paus",
        "deskripsi": "Kalau game di paus(e) kan berhenti main nya"
    },
    {
        "soal": "Sehabis olahraga",
        "jawaban": "Air minum",
        "deskripsi": "Abis olahraga pasti haus kan"
    },
    {
        "soal": "Di tiup angin berkibar di setiap negara",
        "jawaban": "Jemuran",
        "deskripsi": "Disetiap negara orang menjemur pakaiannya"
    },
    {
        "soal": "Kalo haus minum",
        "jawaban": "Aja",
        "deskripsi": "Minum aja ntar juga ga aus"
    },
    {
        "soal": "Hayam wuruk memerintah kerajaan?",
        "jawaban": "Jamandulu",
        "deskripsi": "Ya iyalah… masa jaman sekarang"
    },
    {
        "soal": "Jawab dengan benar. dunia ini terdiri dari lima …",
        "jawaban": "Benar",
        "deskripsi": "Kan sudah saya bilang jawab dengan benar"
    }
]
